gladier_tools/__init__.py
gladier_tools/version.py
gladier_tools/experimental/__init__.py
gladier_tools/experimental/base.py
gladier_tools/experimental/globus/__init__.py
gladier_tools/experimental/globus/mkdir.py
gladier_tools/globus/__init__.py
gladier_tools/globus/transfer.py
gladier_tools/posix/__init__.py
gladier_tools/posix/asymmetric_decrypt.py
gladier_tools/posix/asymmetric_encrypt.py
gladier_tools/posix/decrypt.py
gladier_tools/posix/encrypt.py
gladier_tools/posix/https_download_file.py
gladier_tools/posix/shell_cmd.py
gladier_tools/posix/tar.py
gladier_tools/posix/untar.py
gladier_tools/publish/__init__.py
gladier_tools/publish/publish.py
gladier_tools/publish/publishv2.py
gladier_tools/tests/__init__.py
gladier_tools/tests/experimental/__init__.py
gladier_tools/tests/experimental/globus/__init__.py
gladier_tools/tests/experimental/globus/test_mkdir.py
gladier_tools/tests/posix/__init__.py
gladier_tools/tests/posix/conftest.py
gladier_tools/tests/posix/mocks.py
gladier_tools/tests/posix/test_decrypt.py
gladier_tools/tests/posix/test_encrypt.py
gladier_tools/tests/posix/test_gladier_tools.py
gladier_tools/tests/posix/test_shell_cmd.py
gladier_tools/tests/posix/test_tar.py
gladier_tools/tests/posix/test_untar.py
gladier_tools/tests/publish/__init__.py
gladier_tools/tests/publish/test_publish.py
gladier_tools/tests/publish/test_publishv2.py
gladier_tools-0.5.4.dist-info/LICENSE
gladier_tools-0.5.4.dist-info/METADATA
gladier_tools-0.5.4.dist-info/WHEEL
gladier_tools-0.5.4.dist-info/top_level.txt
gladier_tools-0.5.4.dist-info/RECORD
