Metadata-Version: 2.1
Name: gladier-tools
Version: 0.5.4
Summary: A set of reusable Gladier Tools
Home-page: https://github.com/globus-gladier/gladier-tools
Maintainer: The Gladier Team
Maintainer-email: 
License: Apache 2.0
Classifier: Intended Audience :: Science/Research
Classifier: Intended Audience :: Developers
Classifier: License :: OSI Approved :: Apache Software License
Classifier: Operating System :: POSIX
Classifier: Operating System :: MacOS :: MacOS X
Classifier: Programming Language :: Python
Classifier: Programming Language :: Python :: 3.6
Classifier: Programming Language :: Python :: 3.7
Classifier: Programming Language :: Python :: 3.8
Classifier: Programming Language :: Python :: 3.9
License-File: LICENSE
Requires-Dist: gladier >=0.9.0
